geohexgrid/__init__.py
geohexgrid/main.py
geohexgrid-2.1.2.dist-info/METADATA
geohexgrid-2.1.2.dist-info/WHEEL
geohexgrid-2.1.2.dist-info/RECORD
