Metadata-Version: 2.4
Name: geohexgrid
Version: 2.1.2
Summary: A Python library for making geographic flat-top hexagon grids like QGIS's `create grid` function
Project-URL: Repository, https://github.com/mrcagney/geohexgrid
Author-email: Alex Raichev <araichev@mrcagney.com>
License-Expression: MIT
Requires-Python: >=3.10
Requires-Dist: geopandas>=0.11.1
